plotfa/__init__.py
plotfa/plotfa.py
plotfa-0.0.5.dist-info/LICENSE
plotfa-0.0.5.dist-info/METADATA
plotfa-0.0.5.dist-info/WHEEL
plotfa-0.0.5.dist-info/top_level.txt
plotfa-0.0.5.dist-info/RECORD
