Metadata-Version: 2.1
Name: plotfa
Version: 0.0.5
Summary: Create Persian plots using matplotlob/seaborn
Home-page: https://github.com/TheAlbatrossCodes/plotfa
Author: Behnam Sajadifar
Author-email: behnamsajadi@gmail.com
License: GPLv3
Platform: UNKNOWN
Classifier: Development Status :: 3 - Alpha
Classifier: Intended Audience :: Developers
Classifier: License :: OSI Approved :: GNU General Public License v3 (GPLv3)
Requires-Dist: matplotlib
Requires-Dist: seaborn
Requires-Dist: arabic-reshaper
Requires-Dist: python-bidi
